cptree/__init__.py
cptree/checksum.py
cptree/cli.py
cptree/common.py
cptree/cptree.py
cptree/exception_handler.py
cptree/exceptions.py
cptree/exclude.py
cptree/progress.py
cptree/shell.py
cptree/verify.py
cptree/version.py
cptree/watcher.py
cptree-0.2.5.dist-info/entry_points.txt
cptree-0.2.5.dist-info/LICENSE
cptree-0.2.5.dist-info/WHEEL
cptree-0.2.5.dist-info/METADATA
cptree-0.2.5.dist-info/RECORD
